[
  {
    "temperature": 22.52,
    "humidity": 89.52,
    "pressure": 1009.97,
    "timestamp": "2025-11-21 20:35:33"
  },
  {
    "temperature": 22.52,
    "humidity": 89.52,
    "pressure": 1009.93,
    "timestamp": "2025-11-21 20:35:38"
  },
  {
    "temperature": 22.52,
    "humidity": 89.52,
    "pressure": 1009.96,
    "timestamp": "2025-11-21 20:35:43"
  },
  {
    "temperature": 22.49,
    "humidity": 89.64,
    "pressure": 1011.1,
    "timestamp": "2025-11-21 22:37:28"
  },
  {
    "temperature": 22.58,
    "humidity": 89.42,
    "pressure": 1011.15,
    "timestamp": "2025-11-21 22:47:14"
  },
  {
    "temperature": 22.8,
    "humidity": 88.92,
    "pressure": 1010.95,
    "timestamp": "2025-11-21 23:10:21"
  },
  {
    "temperature": 22.81,
    "humidity": 88.57,
    "pressure": 1010.97,
    "timestamp": "2025-11-21 23:27:43"
  },
  {
    "temperature": 22.78,
    "humidity": 88.57,
    "pressure": 1011.1,
    "timestamp": "2025-11-21 23:37:09"
  },
  {
    "temperature": 22.69,
    "humidity": 84.06,
    "pressure": 1011.18,
    "timestamp": "2025-11-21 23:46:45"
  },
  {
    "temperature": 24.34,
    "humidity": 84.08,
    "pressure": 1011.56,
    "timestamp": "2025-11-22 00:51:16"
  },
  {
    "temperature": 24.35,
    "humidity": 84.88,
    "pressure": 1011.81,
    "timestamp": "2025-11-22 02:21:00"
  },
  {
    "temperature": 24.14,
    "humidity": 85.86,
    "pressure": 1012.03,
    "timestamp": "2025-11-22 03:25:01"
  },
  {
    "temperature": 24.38,
    "humidity": 85.3,
    "pressure": 1012.04,
    "timestamp": "2025-11-22 03:48:13"
  },
  {
    "temperature": 24.58,
    "humidity": 84.96,
    "pressure": 1012.27,
    "timestamp": "2025-11-22 04:12:45"
  },
  {
    "temperature": 23.59,
    "humidity": 85.27,
    "pressure": 1012.47,
    "timestamp": "2025-11-22 04:34:27"
  },
  {
    "temperature": 23.27,
    "humidity": 83.9,
    "pressure": 1012.52,
    "timestamp": "2025-11-22 04:49:04"
  }
]